Metadata-Version: 1.1
Name: asdconfigobj
Version: 5.1.0.dev0
Summary: Config file reading, writing and validation.
Home-page: https://github.com/DiffSK/configobj
Author: Rob Dennis, Eli Courtwright (Michael Foord & Nicola Larosa original maintainers)
Author-email: rdennis+configobj@gmail.com, eli@courtwright.org, fuzzyman@voidspace.co.uk, nico@tekNico.net
License: BSD (2 clause)
Keywords: config,ini,dictionary,application,admin,sysadmin,configuration,validation
Platform: UNKNOWN
Classifier: Development Status :: 6 - Mature
Classifier: Intended Audience :: Developers
Classifier: License :: OSI Approved :: BSD License
Classifier: Programming Language :: Python
Classifier: Programming Language :: Python :: 2
Classifier: Programming Language :: Python :: 2.6
Classifier: Programming Language :: Python :: 2.7
Classifier: Programming Language :: Python :: 3
Classifier: Programming Language :: Python :: 3.3
Classifier: Programming Language :: Python :: 3.4
Classifier: Programming Language :: Python :: 3.5
Classifier: Programming Language :: Python :: 3.6
Classifier: Operating System :: OS Independent
Classifier: Topic :: Software Development :: Libraries
Classifier: Topic :: Software Development :: Libraries :: Python Modules
